nonebot_plugin_starzai_plugin_memu/__init__.py
nonebot_plugin_starzai_plugin_memu/config.py
nonebot_plugin_starzai_plugin_memu-1.0.2.dist-info/METADATA
nonebot_plugin_starzai_plugin_memu-1.0.2.dist-info/WHEEL
nonebot_plugin_starzai_plugin_memu-1.0.2.dist-info/top_level.txt
nonebot_plugin_starzai_plugin_memu-1.0.2.dist-info/RECORD
