Metadata-Version: 2.1
Name: nonebot-plugin-starzai-plugin-memu
Version: 1.0.2
Summary: 星崽BOt-菜单
Requires-Python: <4.0,>=3.8
Requires-Dist: nonebot2
Requires-Dist: nonebot-adapter-onebot
